flashdeberta/__init__.py
flashdeberta/model.py
flashdeberta/ops/__init__.py
flashdeberta/ops/flash_attention.py
flashdeberta/ops/flash_attention_bias.py
flashdeberta/ops/flash_attention_varlen.py
flashdeberta/padding.py
flashdeberta/utils.py
flashdeberta-0.0.7.dist-info/METADATA
flashdeberta-0.0.7.dist-info/WHEEL
flashdeberta-0.0.7.dist-info/licenses/LICENSE
flashdeberta-0.0.7.dist-info/RECORD
