Metadata-Version: 2.4
Name: flashDeBERTa
Version: 0.0.7
Summary: Memory and compute efficient DeBERTa models.
License: Apache-2.0
License-File: LICENSE
Author: knowledgator.com
Requires-Python: >=3.10,<4.0
Classifier: License :: OSI Approved :: Apache Software License
Classifier: Programming Language :: Python :: 3
Classifier: Programming Language :: Python :: 3.10
Classifier: Programming Language :: Python :: 3.11
Classifier: Programming Language :: Python :: 3.12
Classifier: Programming Language :: Python :: 3.13
Classifier: Programming Language :: Python :: 3.14
Requires-Dist: einops (>=0.7.0)
Requires-Dist: torch (>=2.1.0)
Requires-Dist: transformers (>=4.30.0)
Requires-Dist: triton (>=3.0.0)
